fullhunt/__init__.py
fullhunt/fullhunt_main.py
fullhunt_api-0.6.dist-info/METADATA
fullhunt_api-0.6.dist-info/WHEEL
fullhunt_api-0.6.dist-info/top_level.txt
fullhunt_api-0.6.dist-info/RECORD
