Metadata-Version: 2.1
Name: fullhunt_api
Version: 0.6
Summary: Library for working with Fullhunt.io API
Home-page: https://github.com/egor251/fullhunt_api
Author: egor251
Author-email: 
Project-URL: GitHub, https://github.com/egor251/fullhunt_api
Keywords: files speedfiles
Classifier: Programming Language :: Python :: 3.11
Classifier: License :: OSI Approved :: MIT License
Classifier: Operating System :: OS Independent
Requires-Python: >=3.8
Requires-Dist: requests>=2.25.1
